oralchess/__init__.py
oralchess/core.py
oralchess-0.1.0.dist-info/licenses/LICENSE
oralchess-0.1.0.dist-info/METADATA
oralchess-0.1.0.dist-info/WHEEL
oralchess-0.1.0.dist-info/top_level.txt
oralchess-0.1.0.dist-info/RECORD
