Metadata-Version: 2.4
Name: oralchess
Version: 0.1.0
Summary: OralChess: A simple chess engine with minimax and optional oral AI integration
Author-email: Anonym <xyoubotz@gmail.com>
License: MIT
Project-URL: Homepage, https://github.com/ALFARABIqs/oralchess
Requires-Python: >=3.8
License-File: LICENSE
Requires-Dist: python-chess>=1.999
Dynamic: license-file
